MANIFEST.in
README.txt
setup.py
c2/__init__.py
c2.app.replaceword.egg-info/PKG-INFO
c2.app.replaceword.egg-info/SOURCES.txt
c2.app.replaceword.egg-info/dependency_links.txt
c2.app.replaceword.egg-info/entry_points.txt
c2.app.replaceword.egg-info/namespace_packages.txt
c2.app.replaceword.egg-info/not-zip-safe
c2.app.replaceword.egg-info/requires.txt
c2.app.replaceword.egg-info/top_level.txt
c2/app/__init__.py
c2/app/replaceword/__init__.py
c2/app/replaceword/configure.zcml
c2/app/replaceword/tests.py
c2/app/replaceword/version.txt
c2/app/replaceword/browser/__init__.py
c2/app/replaceword/browser/configure.zcml
c2/app/replaceword/browser/replace.pt
c2/app/replaceword/browser/replace.py
c2/app/replaceword/profiles/default/controlpanel.xml
c2/app/replaceword/profiles/default/metadata.xml
docs/HISTORY.txt
docs/INSTALL.txt
docs/LICENSE.GPL
docs/LICENSE.txt