Metadata-Version: 1.0
Name: c2.app.replaceword
Version: 1.0a1
Summary: This product is word replace for content for Plone
Home-page: http://www.cmscom.jp
Author: Manabu TERADA
Author-email: terada@cmscom.jp
License: GPL
Keywords: plone content replace
Platform: UNKNOWN
Classifier: Framework :: Plone
Classifier: Programming Language :: Python
